tabled/__init__.py
tabled/_codecs.py
tabled/base.py
tabled/compare_tables.py
tabled/html.py
tabled/join_tables.py
tabled/misc.py
tabled/multi.py
tabled/util.py
tabled/wrappers.py
tabled/tests/__init__.py
tabled/tests/compare_tables_test.py
tabled/tests/data.py
tabled/tests/generate_data.py
tabled/tests/join_tables.py
tabled/tests/test_base.py
tabled/tests/util.py
tabled-0.1.26.dist-info/LICENSE
tabled-0.1.26.dist-info/METADATA
tabled-0.1.26.dist-info/WHEEL
tabled-0.1.26.dist-info/top_level.txt
tabled-0.1.26.dist-info/RECORD
