Metadata-Version: 2.1
Name: tabled
Version: 0.1.26
Summary: A (key-value) data-object-layer to get (pandas) tables from a variety of sources with ease
Home-page: https://github.com/i2mint/tabled
Author: Thor Whalen
License: apache-2.0
Platform: any
License-File: LICENSE
Requires-Dist: pandas
Requires-Dist: dol
Requires-Dist: i2
Requires-Dist: charset-normalizer
Requires-Dist: pyarrow
Requires-Dist: lxml
Provides-Extra: test
Requires-Dist: pyarrow; extra == "test"
Requires-Dist: requests; extra == "test"
